curlyfries113_blend_x_glb/__init__.py
curlyfries113_blend_x_glb/blender_export.py
curlyfries113_blend_x_glb-1.0.1.dist-info/WHEEL
curlyfries113_blend_x_glb-1.0.1.dist-info/entry_points.txt
curlyfries113_blend_x_glb-1.0.1.dist-info/METADATA
curlyfries113_blend_x_glb-1.0.1.dist-info/RECORD
