Metadata-Version: 2.4
Name: curlyfries113.blend-x-glb
Version: 1.0.1
Summary: Simple Blend file to GLB converter, using Blender
License-Expression: AGPL-3.0-or-later
Requires-Dist: beaupy>=3.11.0
Requires-Dist: typer>=0.21.1
Requires-Python: >=3.13
